iobat/__init__.py
iobat/cli.py
iobat/iobat.py
iobat-0.0.1.dist-info/AUTHORS.rst
iobat-0.0.1.dist-info/LICENSE
iobat-0.0.1.dist-info/METADATA
iobat-0.0.1.dist-info/WHEEL
iobat-0.0.1.dist-info/entry_points.txt
iobat-0.0.1.dist-info/top_level.txt
iobat-0.0.1.dist-info/RECORD
