Metadata-Version: 2.1
Name: iobat
Version: 0.0.1
Summary: iobat.
Home-page: https://github.com/jakobluettgau/iobat
Author: Jakob Luettgau
Author-email: jakobluettgau@gmail.com
License: GNU General Public License v3
Keywords: iobat
Platform: UNKNOWN
Classifier: Development Status :: 2 - Pre-Alpha
Classifier: Intended Audience :: Developers
Classifier: License :: OSI Approved :: GNU General Public License v3 (GPLv3)
Classifier: Natural Language :: English
Classifier: Programming Language :: Python :: 3
Classifier: Programming Language :: Python :: 3.5
Classifier: Programming Language :: Python :: 3.6
Classifier: Programming Language :: Python :: 3.7
Classifier: Programming Language :: Python :: 3.8
Requires-Python: >=3.5
